pbx_admin/__init__.py
pbx_admin/apps.py
pbx_admin/conf.py
pbx_admin/consts.py
pbx_admin/data.py
pbx_admin/decorators.py
pbx_admin/fields.py
pbx_admin/form_fields.py
pbx_admin/forms.py
pbx_admin/handlers.py
pbx_admin/options.py
pbx_admin/paginator.py
pbx_admin/py.typed
pbx_admin/runtests.py
pbx_admin/sites.py
pbx_admin/utils.py
pbx_admin/widgets.py
pbx_admin/migrations/0001_count_estimate.py
pbx_admin/migrations/__init__.py
pbx_admin/static/pbx_admin/css/login.css
pbx_admin/static/pbx_admin/css/main.css
pbx_admin/static/pbx_admin/css/main.css.map
pbx_admin/static/pbx_admin/css/main.min.css
pbx_admin/static/pbx_admin/css/main.min.css.map
pbx_admin/static/pbx_admin/fonts/FontAwesome.otf
pbx_admin/static/pbx_admin/fonts/MaterialDesignIcons.eot
pbx_admin/static/pbx_admin/fonts/MaterialDesignIcons.svg
pbx_admin/static/pbx_admin/fonts/MaterialDesignIcons.ttf
pbx_admin/static/pbx_admin/fonts/MaterialDesignIcons.woff
pbx_admin/static/pbx_admin/fonts/MaterialDesignIcons.woff2
pbx_admin/static/pbx_admin/fonts/OpenSans-Bold.eot
pbx_admin/static/pbx_admin/fonts/OpenSans-Bold.svg
pbx_admin/static/pbx_admin/fonts/OpenSans-Bold.ttf
pbx_admin/static/pbx_admin/fonts/OpenSans-Bold.woff
pbx_admin/static/pbx_admin/fonts/OpenSans-BoldItalic.eot
pbx_admin/static/pbx_admin/fonts/OpenSans-BoldItalic.svg
pbx_admin/static/pbx_admin/fonts/OpenSans-BoldItalic.ttf
pbx_admin/static/pbx_admin/fonts/OpenSans-BoldItalic.woff
pbx_admin/static/pbx_admin/fonts/OpenSans-Extrabold.eot
pbx_admin/static/pbx_admin/fonts/OpenSans-Extrabold.svg
pbx_admin/static/pbx_admin/fonts/OpenSans-Extrabold.ttf
pbx_admin/static/pbx_admin/fonts/OpenSans-Extrabold.woff
pbx_admin/static/pbx_admin/fonts/OpenSans-ExtraboldItalic.eot
pbx_admin/static/pbx_admin/fonts/OpenSans-ExtraboldItalic.svg
pbx_admin/static/pbx_admin/fonts/OpenSans-ExtraboldItalic.ttf
pbx_admin/static/pbx_admin/fonts/OpenSans-ExtraboldItalic.woff
pbx_admin/static/pbx_admin/fonts/OpenSans-Italic.eot
pbx_admin/static/pbx_admin/fonts/OpenSans-Italic.svg
django_pbx_admin-1.35.1.dist-info/METADATA
django_pbx_admin-1.35.1.dist-info/WHEEL
django_pbx_admin-1.35.1.dist-info/top_level.txt
django_pbx_admin-1.35.1.dist-info/RECORD
